aim/__init__.py
aim/__version__.py
aim/cli/__init__.py
aim/cli/deploy.py
aim/deploy/__init__.py
aim/deploy/docker.py
aim/deploy/docker_image.py
aim/deploy/generic.py
aim/deploy/docker/__init__.py
aim/deploy/docker/bla.py
aim/deploy/docker/build.py
aim/deploy/docker/configs.py
aim/deploy/docker/docker_ops_prep.py
aim/deploy/docker/server_prep.py
aim/deploy/docker/utils.py
aim/deploy/docker/_ops/Dockerfile.py
aim/deploy/docker/_ops/__init__.py
aim/deploy/docker/_ops/requirements.txt.py
aim/deploy/docker/_server_files/__init__.py
aim/deploy/docker/_server_files/app.py
aim/engine/__init__.py
aim/engine/aim_model.py
aim/engine/metadata.py
aim/engine/representation.py
aim/engine/deployables/__init__.py
aim/engine/deployables/configs.py
aim/engine/deployables/onnx_runtime.py
aim/export/__init__.py
aim/export/metadata.py
aim/export/pytorch.py
aim/export/utils.py
aim/export/wrapper.py
aim/origin/__init__.py
aim/origin/metadata.py
aim/origin/wrapper.py
aimd-0.1.1.data/data/data/deploy/_ops/Dockerfile
aimd-0.1.1.data/data/data/deploy/_ops/requirements.txt
aimd-0.1.1.data/data/data/deploy/_server_files/app.py
aimd-0.1.1.dist-info/LICENSE
aimd-0.1.1.dist-info/METADATA
aimd-0.1.1.dist-info/WHEEL
aimd-0.1.1.dist-info/entry_points.txt
aimd-0.1.1.dist-info/top_level.txt
aimd-0.1.1.dist-info/RECORD
